{"displayTopicName":"Gemara Kiddushin","topicTokens":[{"text":"Gemara Kiddushin","type":"text"}],"paragraphsBySubtopic":{"Gemara Kiddushin":[{"tokens":[{"text":"Browse ","type":"text"},{"type":"italics","tokens":[{"text":"Meseches Kiddushin","type":"text"}]},{"text":" by Perek or by Daf:","type":"text"}],"type":"text-line"},{"type":"table_list","alignment":null,"rtl":false,"items":[{"list":false,"hidden":false,"tokens":[{"text":"Perakim","type":"local","tokens":[{"text":"Perakim","type":"text"}],"targetSubtopic":"Perakim","targetTopic":"Gemara Kiddushin","enclosingTopic":"Gemara Kiddushin","enclosingSubtopic":"Gemara Kiddushin"}]},{"list":false,"hidden":false,"tokens":[{"text":"Dafim","type":"local","tokens":[{"text":"Dafim","type":"text"}],"targetSubtopic":"Dafim","targetTopic":"Gemara Kiddushin","enclosingTopic":"Gemara Kiddushin","enclosingSubtopic":"Gemara Kiddushin"}]}]}],"Perakim":[{"type":"table_list","alignment":null,"rtl":false,"items":[{"list":false,"hidden":false,"tokens":[{"text":"Ha’ish Mekadesh","type":"global","tokens":[{"text":"Ha’ish Mekadesh","type":"text"}],"pathString":"Ha’ish_Mekadesh","enclosingTopic":"Gemara Kiddushin","enclosingSubtopic":"Perakim"}]}]}],"Dafim":[{"type":"table_list","alignment":null,"rtl":false,"items":[{"list":false,"hidden":false,"tokens":[{"text":"41a","type":"global","tokens":[{"text":"41a","type":"text"}],"pathString":"Kiddushin_41a","enclosingTopic":"Gemara Kiddushin","enclosingSubtopic":"Dafim"}]}]}]}}