{"displayTopicName":"Gemaras on Mishnah on Kiddushin 41a","topicTokens":[{"text":"Gemaras on Mishnah on Kiddushin 41a","type":"text"}],"paragraphsBySubtopic":{"Gemaras on Mishnah on Kiddushin 41a":[{"text":"These are the Gemaras following ","type":"text"},{"text":"the Mishnah on Kiddushin 41a","type":"global","tokens":[{"text":"the Mishnah on Kiddushin 41a","type":"text"}],"pathString":"Mishnah_Ha’ish_Mekadesh","enclosingTopic":"Gemaras on Mishnah on Kiddushin 41a","enclosingSubtopic":"Gemaras on Mishnah on Kiddushin 41a"},{"text":":\n","type":"text"},{"topLevelNodes":[{"ordinal":"1","ordered":true,"tokensOfLine":[{"text":"The Gemara of hashta b’slucho mekadesh","type":"global","tokens":[{"text":"The Gemara of hashta b’slucho mekadesh","type":"text"}],"pathString":"Hashta_B’shlucho_Mekadesh","enclosingTopic":"Gemaras on Mishnah on Kiddushin 41a","enclosingSubtopic":"Gemaras on Mishnah on Kiddushin 41a"},{"text":" (","type":"text"},{"type":"bold","tokens":[{"text":"גמ’","type":"text"}]},{"text":" השתא ... מלמיתב ארמלו, ‎41a:9-23)","type":"text"}],"children":[]},{"ordinal":"2","ordered":true,"tokensOfLine":[{"text":"The Gemara of k’sh’hi na’ara in","type":"global","tokens":[{"text":"The Gemara of k’sh’hi na’ara in","type":"text"}],"pathString":"Ha’ish_mekadesh_es_bito","enclosingTopic":"Gemaras on Mishnah on Kiddushin 41a","enclosingSubtopic":"Gemaras on Mishnah on Kiddushin 41a"},{"text":" (האיש מקדש את ... אני רוצה, ‎41a:23-29)","type":"text"}],"children":[]},{"ordinal":"3","ordered":true,"tokensOfLine":[{"text":"[![The Gemara of shlichus menalan]] (שליחות מנלן, ‎41a:29-42a:32)","type":"text"}],"children":[]},{"ordinal":"3","ordered":true,"tokensOfLine":[{"text":"[![The Gemara of yisomim sh’bo’u lichlok]] (אמר רב נחמן אמר שמואל, ‎42a:32-42b:2)","type":"text"}],"children":[]},{"ordinal":"3","ordered":true,"tokensOfLine":[{"text":"[![The Gemara of achin sh’chalku]] (אמר רב נחמן האחין שחלקו, ‎42b:2-43:41)","type":"text"}],"children":[]}],"type":"outline"}]}}