{"displayTopicName":"_Itaf’al_ Past Tense","topicTokens":[{"type":"italics","tokens":[{"text":"Itaf’al","type":"text"}]},{"text":" Past Tense","type":"text"}],"paragraphsBySubtopic":{"Itaf’al Past Tense":[{"text":"The ","type":"text"},{"text":"_itaf’al_ binyan","type":"global","tokens":[{"type":"italics","tokens":[{"text":"itaf’al","type":"text"}]},{"text":" binyan","type":"text"}],"pathString":"Itaf’al","enclosingTopic":"Itaf’al Past Tense","enclosingSubtopic":"Itaf’al Past Tense"},{"text":" has a ","type":"text"},{"text":"past tense","type":"global","tokens":[{"text":"past tense","type":"text"}],"pathString":"Past_tense","enclosingTopic":"Itaf’al Past Tense","enclosingSubtopic":"Itaf’al Past Tense"},{"text":", which is one of the ","type":"text"},{"text":"“tenses” of the _itaf’al_ binyan","type":"global","tokens":[{"text":"“tenses” of the ","type":"text"},{"type":"italics","tokens":[{"text":"itaf’al","type":"text"}]},{"text":" binyan","type":"text"}],"pathString":"Itaf’al_Tenses","enclosingTopic":"Itaf’al Past Tense","enclosingSubtopic":"Itaf’al Past Tense"},{"text":".\nThe ","type":"text"},{"text":"_itaf’al_ past tense","type":"global","tokens":[{"type":"italics","tokens":[{"text":"itaf’al","type":"text"}]},{"text":" past tense","type":"text"}],"pathString":"Itaf’al_Past_Tense#Itaf’al_Past_Tense","enclosingTopic":"Itaf’al Past Tense","enclosingSubtopic":"Itaf’al Past Tense"},{"text":" does not occur frequently enough in the Talmud to determine its regular conjugations. This is the conjugation pattern of the ","type":"text"},{"type":"italics","tokens":[{"text":"itaf’al","type":"text"}]},{"text":" in ","type":"text"},{"type":"italics","tokens":[{"text":"Targum Onkolos","type":"text"}]},{"text":" for ","type":"text"},{"text":"regular shorushim","type":"global","tokens":[{"text":"regular shorushim","type":"text"}],"pathString":"Regular_shorushim","enclosingTopic":"Itaf’al Past Tense","enclosingSubtopic":"Itaf’al Past Tense"},{"text":" like מסר:\n","type":"text"},{"type":"table","rows":[[{"tokens":[]},{"tokens":[{"type":"bold","tokens":[{"text":"Singular","type":"text"}]}],"colspan":2},{"tokens":[],"merge":true},{"tokens":[{"type":"bold","tokens":[{"text":"Plural","type":"text"}]}],"colspan":2},{"tokens":[],"merge":true}],[{"tokens":[{"type":"bold","tokens":[{"text":"First- ","type":"text"},{"type":"html_element","tokenInsertions":[],"html":"<br>"},{"text":" Person","type":"text"}]}]},{"tokens":[{"text":"אִיתַּפְקַדִית ","type":"text"},{"type":"html_element","tokenInsertions":[],"html":"<br>"},{"type":"html_element","tokenInsertions":[],"html":"<br>"},{"text":" ","type":"text"},{"type":"italics","tokens":[{"text":"itafkadis","type":"text"}]},{"text":" ","type":"text"},{"type":"html_element","tokenInsertions":[],"html":"<br>"},{"type":"html_element","tokenInsertions":[],"html":"<br>"},{"type":"html_element","tokenInsertions":[],"html":"<br>"},{"text":" I was ","type":"text"},{"type":"html_element","tokenInsertions":[],"html":"<br>"},{"text":" deposited","type":"text"}],"colspan":2},{"tokens":[],"merge":true},{"tokens":[{"text":"אִתַּפְקַדְנָא ","type":"text"},{"type":"html_element","tokenInsertions":[],"html":"<br>"},{"type":"html_element","tokenInsertions":[],"html":"<br>"},{"text":" ","type":"text"},{"type":"italics","tokens":[{"text":"itafkadnau","type":"text"}]},{"text":" ","type":"text"},{"type":"html_element","tokenInsertions":[],"html":"<br>"},{"type":"html_element","tokenInsertions":[],"html":"<br>"},{"type":"html_element","tokenInsertions":[],"html":"<br>"},{"text":" we were","type":"text"},{"type":"html_element","tokenInsertions":[],"html":"<br>"},{"text":" deposited","type":"text"}],"colspan":2},{"tokens":[],"merge":true}],[{"tokens":[{"type":"bold","tokens":[{"text":"Second-Person","type":"text"}]}]},{"tokens":[{"text":"אִתַּפְקַדְתָּא","type":"text"},{"type":"html_element","tokenInsertions":[],"html":"<br>"},{"text":" אִתַּפְקַדְתְּ ","type":"text"},{"type":"html_element","tokenInsertions":[],"html":"<br>"},{"type":"html_element","tokenInsertions":[],"html":"<br>"},{"text":" ","type":"text"},{"type":"italics","tokens":[{"text":"itafkadtau,","type":"text"},{"type":"html_element","tokenInsertions":[],"html":"<br>"},{"text":" itafkadt","type":"text"}]},{"text":" ","type":"text"},{"type":"html_element","tokenInsertions":[],"html":"<br>"},{"type":"html_element","tokenInsertions":[],"html":"<br>"},{"type":"html_element","tokenInsertions":[],"html":"<br>"},{"text":" you [male] ","type":"text"},{"type":"html_element","tokenInsertions":[],"html":"<br>"},{"text":" were deposited","type":"text"}]},{"tokens":[{"text":"אִתַּפְקַדְתְּ ","type":"text"},{"type":"html_element","tokenInsertions":[],"html":"<br>"},{"type":"html_element","tokenInsertions":[],"html":"<br>"},{"text":" ","type":"text"},{"type":"italics","tokens":[{"text":"itafkadt","type":"text"}]},{"text":" ","type":"text"},{"type":"html_element","tokenInsertions":[],"html":"<br>"},{"type":"html_element","tokenInsertions":[],"html":"<br>"},{"type":"html_element","tokenInsertions":[],"html":"<br>"},{"text":" you [female] ","type":"text"},{"type":"html_element","tokenInsertions":[],"html":"<br>"},{"text":" were deposited","type":"text"}]},{"tokens":[{"text":"אִתַּפְקַדְתּוּן ","type":"text"},{"type":"html_element","tokenInsertions":[],"html":"<br>"},{"type":"html_element","tokenInsertions":[],"html":"<br>"},{"text":" ","type":"text"},{"type":"italics","tokens":[{"text":"itafkadtun","type":"text"}]},{"text":" ","type":"text"},{"type":"html_element","tokenInsertions":[],"html":"<br>"},{"type":"html_element","tokenInsertions":[],"html":"<br>"},{"type":"html_element","tokenInsertions":[],"html":"<br>"},{"text":" you [men] were ","type":"text"},{"type":"html_element","tokenInsertions":[],"html":"<br>"},{"text":" deposited","type":"text"}]},{"tokens":[{"text":"אִתַּפְקַדְתִּין ","type":"text"},{"type":"html_element","tokenInsertions":[],"html":"<br>"},{"type":"html_element","tokenInsertions":[],"html":"<br>"},{"text":" ","type":"text"},{"type":"italics","tokens":[{"text":"itafkadtin","type":"text"}]},{"text":" ","type":"text"},{"type":"html_element","tokenInsertions":[],"html":"<br>"},{"type":"html_element","tokenInsertions":[],"html":"<br>"},{"type":"html_element","tokenInsertions":[],"html":"<br>"},{"text":" you [women] were ","type":"text"},{"type":"html_element","tokenInsertions":[],"html":"<br>"},{"text":" deposited","type":"text"}]}],[{"tokens":[{"type":"bold","tokens":[{"text":"Third- ","type":"text"},{"type":"html_element","tokenInsertions":[],"html":"<br>"},{"text":" Person","type":"text"}]}]},{"tokens":[{"text":"‎אִתַּפְקַד ","type":"text"},{"type":"html_element","tokenInsertions":[],"html":"<br>"},{"type":"html_element","tokenInsertions":[],"html":"<br>"},{"text":" ","type":"text"},{"type":"italics","tokens":[{"text":"itafkad","type":"text"}]},{"text":" ","type":"text"},{"type":"html_element","tokenInsertions":[],"html":"<br>"},{"type":"html_element","tokenInsertions":[],"html":"<br>"},{"type":"html_element","tokenInsertions":[],"html":"<br>"},{"text":" he was deposited","type":"text"}]},{"tokens":[{"text":"אִתַּפְקַדַת‎","type":"text"},{"type":"html_element","tokenInsertions":[],"html":"<br>"},{"type":"html_element","tokenInsertions":[],"html":"<br>"},{"text":" ","type":"text"},{"type":"italics","tokens":[{"text":"itafkadas","type":"text"}]},{"text":" ","type":"text"},{"type":"html_element","tokenInsertions":[],"html":"<br>"},{"type":"html_element","tokenInsertions":[],"html":"<br>"},{"type":"html_element","tokenInsertions":[],"html":"<br>"},{"text":" she was ","type":"text"},{"type":"html_element","tokenInsertions":[],"html":"<br>"},{"text":" deposited","type":"text"}]},{"tokens":[{"text":"‎אִתַּפְקַדוּ ","type":"text"},{"type":"html_element","tokenInsertions":[],"html":"<br>"},{"type":"html_element","tokenInsertions":[],"html":"<br>"},{"text":" ","type":"text"},{"type":"italics","tokens":[{"text":"itafkadu","type":"text"}]},{"text":" ","type":"text"},{"type":"html_element","tokenInsertions":[],"html":"<br>"},{"type":"html_element","tokenInsertions":[],"html":"<br>"},{"type":"html_element","tokenInsertions":[],"html":"<br>"},{"text":" they (men) were deposited","type":"text"}]},{"tokens":[{"text":"אִתַּפְקַדָא ","type":"text"},{"type":"html_element","tokenInsertions":[],"html":"<br>"},{"type":"html_element","tokenInsertions":[],"html":"<br>"},{"text":" ","type":"text"},{"type":"italics","tokens":[{"text":"itafkadau","type":"text"}]},{"text":" ","type":"text"},{"type":"html_element","tokenInsertions":[],"html":"<br>"},{"type":"html_element","tokenInsertions":[],"html":"<br>"},{"type":"html_element","tokenInsertions":[],"html":"<br>"},{"text":" they (women) were deposited","type":"text"}]}]]},{"text":"\n","type":"text"},{"topLevelNodes":[{"ordinal":"-","ordered":false,"tokensOfLine":[{"text":"The ","type":"text"},{"type":"italics","tokens":[{"text":"itaf’al","type":"text"}]},{"text":" past tense corresponds to the ","type":"text"},{"text":"_hif’il_ past tense","type":"global","tokens":[{"type":"italics","tokens":[{"text":"hif’il","type":"text"}]},{"text":" past tense","type":"text"}],"pathString":"Hif’il_Past_Tense","enclosingTopic":"Itaf’al Past Tense","enclosingSubtopic":"Itaf’al Past Tense"},{"text":" of Hebrew.","type":"text"}],"children":[]}],"type":"outline"},{"type":"footnote_lines","lines":[{"superscript":"1","tokens":[{"text":" Because Aramaic was a less-formal spoken language, it often has several versions of the same word. Parentheses indicate letters that sometimes are omitted.","type":"text"}]},{"superscript":"2","tokens":[{"text":" Attempts to vowelize the Gemara are speculative. These conjugations are based on R Yitzchok Frank’s ","type":"text"},{"type":"italics","tokens":[{"text":"Grammar for Gemara","type":"text"}]},{"text":".","type":"text"}]}]}]}}