{"displayTopicName":"_Nif’al_ Future Tense","topicTokens":[{"type":"italics","tokens":[{"text":"Nif’al","type":"text"}]},{"text":" Future Tense","type":"text"}],"paragraphsBySubtopic":{"Nif’al Future Tense":[{"text":"The ","type":"text"},{"type":"italics","tokens":[{"text":"nif’al","type":"text"}]},{"text":" has an ","type":"text"},{"text":"future tense","type":"global","tokens":[{"text":"future tense","type":"text"}],"pathString":"Future_Tense","enclosingTopic":"Nif’al Future Tense","enclosingSubtopic":"Nif’al Future Tense"},{"text":" which is one of the ","type":"text"},{"text":"forms of the nif’al binyan","type":"global","tokens":[{"text":"forms of the nif’al binyan","type":"text"}],"pathString":"Nif’al_Tenses","enclosingTopic":"Nif’al Future Tense","enclosingSubtopic":"Nif’al Future Tense"},{"text":".\n","type":"text"},{"topLevelNodes":[{"ordinal":"-","ordered":false,"tokensOfLine":[{"text":"The ","type":"text"},{"type":"italics","tokens":[{"text":"nif’al","type":"text"}]},{"text":" future tense has ","type":"text"},{"text":"conjugations for regular shorushim","type":"global","tokens":[{"text":"conjugations for regular shorushim","type":"text"}],"pathString":"Nif’al_Future_Tense_for_regular_shorushim","enclosingTopic":"Nif’al Future Tense","enclosingSubtopic":"Nif’al Future Tense"},{"text":". (Conjugations for ","type":"text"},{"text":"irregular shorushim","type":"global","tokens":[{"text":"irregular shorushim","type":"text"}],"pathString":"Irregular_shorushim","enclosingTopic":"Nif’al Future Tense","enclosingSubtopic":"Nif’al Future Tense"},{"text":" are not yet available.)","type":"text"}],"children":[]}],"type":"outline"}]}}