{"displayTopicName":"_Pa’al_ Past Tense","topicTokens":[{"type":"italics","tokens":[{"text":"Pa’al","type":"text"}]},{"text":" Past Tense","type":"text"}],"paragraphsBySubtopic":{"Pa’al Past Tense":[{"text":"The ","type":"text"},{"type":"italics","tokens":[{"text":"pa’al","type":"text"}]},{"text":" binyan has an ","type":"text"},{"text":"past tense","type":"global","tokens":[{"text":"past tense","type":"text"}],"pathString":"Past_tense","enclosingTopic":"Pa’al Past Tense","enclosingSubtopic":"Pa’al Past Tense"},{"text":", which is one of the ","type":"text"},{"text":"forms of the _pa’al_ binyan.","type":"global","tokens":[{"text":"forms of the ","type":"text"},{"type":"italics","tokens":[{"text":"pa’al","type":"text"}]},{"text":" binyan.","type":"text"}],"pathString":"Pa’al_Tenses","enclosingTopic":"Pa’al Past Tense","enclosingSubtopic":"Pa’al Past Tense"},{"text":"\nThe ","type":"text"},{"type":"italics","tokens":[{"text":"pa’al","type":"text"}]},{"text":" past tense follows these conjugations for ","type":"text"},{"text":"regular shorushim","type":"global","tokens":[{"text":"regular shorushim","type":"text"}],"pathString":"Regular_shorushim","enclosingTopic":"Pa’al Past Tense","enclosingSubtopic":"Pa’al Past Tense"},{"text":" like כתב:\n","type":"text"},{"type":"table","rows":[[{"tokens":[]},{"tokens":[{"type":"bold","tokens":[{"text":"Singular","type":"text"}]}],"colspan":2},{"tokens":[],"merge":true},{"tokens":[{"type":"bold","tokens":[{"text":"Plural","type":"text"}]}],"colspan":2},{"tokens":[],"merge":true}],[{"tokens":[{"type":"bold","tokens":[{"text":"First-Person","type":"text"}]}]},{"tokens":[{"text":"כָּתַבְתִּי ","type":"text"},{"type":"html_element","tokenInsertions":[],"html":"<br>"},{"type":"html_element","tokenInsertions":[],"html":"<br>"},{"text":" ","type":"text"},{"type":"italics","tokens":[{"text":"kosavti","type":"text"}]},{"text":" ","type":"text"},{"type":"html_element","tokenInsertions":[],"html":"<br>"},{"type":"html_element","tokenInsertions":[],"html":"<br>"},{"type":"html_element","tokenInsertions":[],"html":"<br>"},{"text":" I wrote","type":"text"}],"colspan":2},{"tokens":[],"merge":true},{"tokens":[{"text":"כָּתַבְנוּ ","type":"text"},{"type":"html_element","tokenInsertions":[],"html":"<br>"},{"type":"html_element","tokenInsertions":[],"html":"<br>"},{"text":" ","type":"text"},{"type":"italics","tokens":[{"text":"kosavnu","type":"text"}]},{"text":" ","type":"text"},{"type":"html_element","tokenInsertions":[],"html":"<br>"},{"type":"html_element","tokenInsertions":[],"html":"<br>"},{"type":"html_element","tokenInsertions":[],"html":"<br>"},{"text":" We wrote","type":"text"}],"colspan":2},{"tokens":[],"merge":true}],[{"tokens":[{"type":"bold","tokens":[{"text":"Second-Person","type":"text"}]}]},{"tokens":[{"text":"כָּתַבְתָּ ","type":"text"},{"type":"html_element","tokenInsertions":[],"html":"<br>"},{"type":"html_element","tokenInsertions":[],"html":"<br>"},{"text":" ","type":"text"},{"type":"italics","tokens":[{"text":"kosavto","type":"text"}]},{"text":" ","type":"text"},{"type":"html_element","tokenInsertions":[],"html":"<br>"},{"type":"html_element","tokenInsertions":[],"html":"<br>"},{"type":"html_element","tokenInsertions":[],"html":"<br>"},{"text":" You [male] wrote","type":"text"}]},{"tokens":[{"text":"כָּתַבְתְּ ","type":"text"},{"type":"html_element","tokenInsertions":[],"html":"<br>"},{"type":"html_element","tokenInsertions":[],"html":"<br>"},{"text":" ","type":"text"},{"type":"italics","tokens":[{"text":"kosavt","type":"text"}]},{"text":" ","type":"text"},{"type":"html_element","tokenInsertions":[],"html":"<br>"},{"type":"html_element","tokenInsertions":[],"html":"<br>"},{"type":"html_element","tokenInsertions":[],"html":"<br>"},{"text":" You [female] wrote","type":"text"}]},{"tokens":[{"text":"כְּתַבְתֶּם ","type":"text"},{"type":"html_element","tokenInsertions":[],"html":"<br>"},{"type":"html_element","tokenInsertions":[],"html":"<br>"},{"text":" ","type":"text"},{"type":"italics","tokens":[{"text":"ksavtem","type":"text"}]},{"text":" ","type":"text"},{"type":"html_element","tokenInsertions":[],"html":"<br>"},{"type":"html_element","tokenInsertions":[],"html":"<br>"},{"type":"html_element","tokenInsertions":[],"html":"<br>"},{"text":" You [males] wrote","type":"text"}]},{"tokens":[{"text":"כְּתַבְתֶּן ","type":"text"},{"type":"html_element","tokenInsertions":[],"html":"<br>"},{"type":"html_element","tokenInsertions":[],"html":"<br>"},{"text":" ","type":"text"},{"type":"italics","tokens":[{"text":"ksavten","type":"text"}]},{"text":" ","type":"text"},{"type":"html_element","tokenInsertions":[],"html":"<br>"},{"type":"html_element","tokenInsertions":[],"html":"<br>"},{"type":"html_element","tokenInsertions":[],"html":"<br>"},{"text":" You [females] wrote","type":"text"}]}],[{"tokens":[{"type":"bold","tokens":[{"text":"Third-Person","type":"text"}]}]},{"tokens":[{"text":"כָּתַב ","type":"text"},{"type":"html_element","tokenInsertions":[],"html":"<br>"},{"type":"html_element","tokenInsertions":[],"html":"<br>"},{"text":" ","type":"text"},{"type":"italics","tokens":[{"text":"kausav","type":"text"}]},{"text":" ","type":"text"},{"type":"html_element","tokenInsertions":[],"html":"<br>"},{"type":"html_element","tokenInsertions":[],"html":"<br>"},{"type":"html_element","tokenInsertions":[],"html":"<br>"},{"text":" He wrote","type":"text"}]},{"tokens":[{"text":"כָּתְבָה ","type":"text"},{"type":"html_element","tokenInsertions":[],"html":"<br>"},{"type":"html_element","tokenInsertions":[],"html":"<br>"},{"text":" ","type":"text"},{"type":"italics","tokens":[{"text":"kausvau","type":"text"}]},{"text":" ","type":"text"},{"type":"html_element","tokenInsertions":[],"html":"<br>"},{"type":"html_element","tokenInsertions":[],"html":"<br>"},{"type":"html_element","tokenInsertions":[],"html":"<br>"},{"text":" She wrote","type":"text"}]},{"tokens":[{"text":"כָּתְבוּ ","type":"text"},{"type":"html_element","tokenInsertions":[],"html":"<br>"},{"type":"html_element","tokenInsertions":[],"html":"<br>"},{"text":" ","type":"text"},{"type":"italics","tokens":[{"text":"kausvu","type":"text"}]},{"text":" ","type":"text"},{"type":"html_element","tokenInsertions":[],"html":"<br>"},{"type":"html_element","tokenInsertions":[],"html":"<br>"},{"type":"html_element","tokenInsertions":[],"html":"<br>"},{"text":" They [male or female] wrote","type":"text"}],"colspan":2},{"tokens":[],"merge":true}]]},{"text":"\n","type":"text"},{"topLevelNodes":[{"ordinal":"-","ordered":false,"tokensOfLine":[{"text":"The ","type":"text"},{"type":"italics","tokens":[{"text":"pa’al","type":"text"}]},{"text":" past tense corresponds to the ","type":"text"},{"text":"_pe’al_ past tense","type":"global","tokens":[{"type":"italics","tokens":[{"text":"pe’al","type":"text"}]},{"text":" past tense","type":"text"}],"pathString":"Pe’al_Past_Tense","enclosingTopic":"Pa’al Past Tense","enclosingSubtopic":"Pa’al Past Tense"},{"text":" of Aramaic.","type":"text"}],"children":[]}],"type":"outline"}]}}