{"displayTopicName":"Ritvah on k’sh’hi na’arah in","topicTokens":[{"text":"Ritvah on k’sh’hi na’arah in","type":"text"}],"paragraphsBySubtopic":{"Ritvah on k’sh’hi na’arah in":[{"text":"Ritvas on ","type":"text"},{"type":"italics","tokens":[{"text":"k’sh’hi na’arah in","type":"text"}]},{"text":":\n","type":"text"},{"topLevelNodes":[{"ordinal":"1","ordered":true,"tokensOfLine":[{"text":"Ritvah D\"H _a’ha d’tanan ha’ish mekadesh es bito_","type":"global","tokens":[{"text":"Ritvah D\"H ","type":"text"},{"type":"italics","tokens":[{"text":"a’ha d’tanan ha’ish mekadesh es bito","type":"text"}]}],"pathString":"Ritvah_D\"H_a’ha_d’tanan_ha’ish_mekadesh_es_bito","enclosingTopic":"Ritvah on k’sh’hi na’arah in","enclosingSubtopic":"Ritvah on k’sh’hi na’arah in"}],"children":[]},{"ordinal":"2","ordered":true,"tokensOfLine":[{"text":"Ritvah D\"H _mesayeh leh l’Rav Yehuda amar Rav_","type":"global","tokens":[{"text":"Ritvah D\"H ","type":"text"},{"type":"italics","tokens":[{"text":"mesayeh leh l’Rav Yehuda amar Rav","type":"text"}]}],"pathString":"Ritvah_D\"H_mesayeh_leh_l’Rav_Yehuda_amar_Rav","enclosingTopic":"Ritvah on k’sh’hi na’arah in","enclosingSubtopic":"Ritvah on k’sh’hi na’arah in"}],"children":[]}],"type":"outline"}]}}