{"displayTopicName":"דקטנה","topicTokens":[{"text":"דקטנה","type":"text"}],"paragraphsBySubtopic":{"דקטנה":[{"text":"The letters דקטנה are probably:\n","type":"text"},{"topLevelNodes":[{"ordinal":"-","ordered":false,"tokensOfLine":[{"text":"The Aramaic prefix ד meaning “that” ","type":"text"},{"type":"html_element","tokenInsertions":[[{"text":"→","type":"global","tokens":[{"text":"→","type":"text"}],"pathString":"Prefix_ד","enclosingTopic":"דקטנה","enclosingSubtopic":"דקטנה"}]],"html":"<small><div class=\"canopy-html-insertion\" data-replacement-number=\"0\"></div></small>"}],"children":[]},{"ordinal":"-","ordered":false,"tokensOfLine":[{"text":"The Aramaic prefix ק which gives a general emphasis ","type":"text"},{"type":"html_element","tokenInsertions":[[{"text":"→","type":"global","tokens":[{"text":"→","type":"text"}],"pathString":"Prefix_ק","enclosingTopic":"דקטנה","enclosingSubtopic":"דקטנה"}]],"html":"<small><div class=\"canopy-html-insertion\" data-replacement-number=\"0\"></div></small>"}],"children":[]}],"type":"outline"}]}}