{"displayTopicName":"כי","topicTokens":[{"text":"כי","type":"text"}],"paragraphsBySubtopic":{"כי":[{"text":"The letters כי are probably the Hebrew word כִּי ","type":"text"},{"type":"italics","tokens":[{"text":"ki","type":"text"}]},{"text":" which can mean “if”, “when”, “because.” ","type":"text"},{"type":"html_element","tokenInsertions":[[{"text":"→","type":"global","tokens":[{"text":"→","type":"text"}],"pathString":"כִּי","enclosingTopic":"כי","enclosingSubtopic":"כי"}]],"html":"<small><div class=\"canopy-html-insertion\" data-replacement-number=\"0\"></div></small>"}]}}